.editorconfig
AUTHORS.rst
CHANGES.md
CONTRIBUTING.rst
INSTALL.rst
LICENSE
MANIFEST.in
Makefile
README.md
pytest.ini
run-tests.sh
setup.cfg
setup.py
docs/Makefile
docs/api.rst
docs/authors.rst
docs/changes.rst
docs/conf.py
docs/configuration.rst
docs/contributing.rst
docs/index.rst
docs/installation.rst
docs/license.rst
docs/make.bat
docs/requirements.txt
docs/usage.rst
invenio_subjects_ddc_german/__init__.py
invenio_subjects_ddc_german/cli.py
invenio_subjects_ddc_german/converter.py
invenio_subjects_ddc_german/reader.py
invenio_subjects_ddc_german/version.py
invenio_subjects_ddc_german/writer.py
invenio_subjects_ddc_german.egg-info/PKG-INFO
invenio_subjects_ddc_german.egg-info/SOURCES.txt
invenio_subjects_ddc_german.egg-info/dependency_links.txt
invenio_subjects_ddc_german.egg-info/entry_points.txt
invenio_subjects_ddc_german.egg-info/not-zip-safe
invenio_subjects_ddc_german.egg-info/requires.txt
invenio_subjects_ddc_german.egg-info/top_level.txt
invenio_subjects_ddc_german/download/__init__.py
invenio_subjects_ddc_german/download/download.py
invenio_subjects_ddc_german/vocabularies/__init__.py
invenio_subjects_ddc_german/vocabularies/subjects_ddc_german.yaml
invenio_subjects_ddc_german/vocabularies/vocabularies.yaml
tests/conftest.py
tests/test_invenio_subjects_ddc.py